altanalyze/.gitignore
altanalyze/.gitignore_global
altanalyze/AltAnalyze.py
altanalyze/AltAnalyzeViewer.py
altanalyze/AltDatabase.zip
altanalyze/AltExonViewer.py
altanalyze/Config.zip
altanalyze/ExpressionBuilder.py
altanalyze/GO_Elite.py
altanalyze/InteractionBuilder.py
altanalyze/LICENSE
altanalyze/LineageProfiler.py
altanalyze/LineageProfilerIterate.py
altanalyze/README.md
altanalyze/RNASeq.py
altanalyze/R_interface.py
altanalyze/UI.py
altanalyze/__init__.py
altanalyze/download.py
altanalyze/export.py
altanalyze/gene_associations.py
altanalyze/mappfinder.py
altanalyze/markerFinder.py
altanalyze/pyper.py
altanalyze/reorder_arrays.py
altanalyze/unique.py
altanalyze/update.py
altanalyze/benchmarking/__init__.py
altanalyze/benchmarking/scripts/IsoformToJunctionCounts.py
altanalyze/benchmarking/scripts/LeafCutterTranslation.py
altanalyze/benchmarking/scripts/__init__.py
altanalyze/build_scripts/AltAnalyze_W7.ico
altanalyze/build_scripts/EnsemblImport.py
altanalyze/build_scripts/EnsemblSQL.py
altanalyze/build_scripts/ExonAnalyze_module.py
altanalyze/build_scripts/ExonArray.py
altanalyze/build_scripts/ExonArrayAffyRules.py
altanalyze/build_scripts/ExonArrayEnsemblRules.py
altanalyze/build_scripts/ExonSeqModule.py
altanalyze/build_scripts/ExtractUniProtFunctAnnot.py
altanalyze/build_scripts/FeatureAlignment.py
altanalyze/build_scripts/GO_parsing.py
altanalyze/build_scripts/GeneSetDownloader.py
altanalyze/build_scripts/IdentifyAltIsoforms.py
altanalyze/build_scripts/JunctionArray.py
altanalyze/build_scripts/JunctionArrayEnsemblRules.py
altanalyze/build_scripts/JunctionSeqModule.py
altanalyze/build_scripts/LiftOverAffy.py
altanalyze/build_scripts/MatchMiRTargetPredictions.py
altanalyze/build_scripts/ParsePGF.py
altanalyze/build_scripts/RefSeqParser.py
altanalyze/build_scripts/SubGeneViewerExport.py
altanalyze/build_scripts/UCSCImport.py
altanalyze/build_scripts/Viewer.icns
altanalyze/build_scripts/Viewer.ico
altanalyze/build_scripts/__init__.py
AltAnalyze-2.1.3.15.dist-info/LICENSE.txt
AltAnalyze-2.1.3.15.dist-info/METADATA
AltAnalyze-2.1.3.15.dist-info/WHEEL
AltAnalyze-2.1.3.15.dist-info/dependency_links.txt
AltAnalyze-2.1.3.15.dist-info/entry_points.txt
AltAnalyze-2.1.3.15.dist-info/top_level.txt
AltAnalyze-2.1.3.15.dist-info/RECORD
