Metadata-Version: 2.1
Name: AltAnalyze
Version: 2.1.3.15
Summary: User Friendly Application for Comprehensive Transcriptome Analysis
Home-page: http://www.altanalyze.org
Author: Nathan Salomonis
Author-email: nathan.salomonis@cchmc.org
License: Apache
Keywords: bioinformatics,transcriptome analysis,gene expression
Platform: UNKNOWN
Classifier: Development Status :: 5 - Production/Stable
Classifier: Intended Audience :: Science/Research
Classifier: Topic :: Scientific/Engineering :: Bio-Informatics
Classifier: License :: OSI Approved :: Apache Software License
Classifier: Programming Language :: Python :: 2.7
Requires-Dist: numpy
Requires-Dist: scipy
Requires-Dist: pillow
Requires-Dist: patsy
Requires-Dist: pandas
Requires-Dist: umap-learn
Requires-Dist: nimfa
Requires-Dist: networkx
Requires-Dist: fastcluster
Requires-Dist: requests
Requires-Dist: lxml
Requires-Dist: community
Requires-Dist: pysam-windows ; "Windows" in sys_platform
Requires-Dist: wxpython ; "Windows" in sys_platform
Requires-Dist: annoy ; "Windows" in sys_platform
Requires-Dist: numba ; "Windows" in sys_platform
Requires-Dist: matplotlib ; "Windows" in sys_platform
Requires-Dist: pysam (==0.13) ; "darwin" in sys_platform
Requires-Dist: sklearn ; "darwin" in sys_platform
Requires-Dist: wxpython ; "darwin" in sys_platform
Requires-Dist: annoy ; "darwin" in sys_platform
Requires-Dist: numba ; "darwin" in sys_platform
Requires-Dist: numba (==0.44.0) ; "linux" in sys_platform
Requires-Dist: sklearn ; "linux" in sys_platform
Requires-Dist: pysam ; "linux" in sys_platform
Requires-Dist: matplotlib ; "linux" in sys_platform
